Metadata-Version: 2.1
Name: Tudjewuj
Version: 0.1
Summary: Privet!
Author-email: dmiro306@gmail.com
